<?xml version="1.0" encoding="UTF-8"?>
<!DOCTYPE plist PUBLIC "-//Apple//DTD PLIST 1.0//EN" "http://www.apple.com/DTDs/PropertyList-1.0.dtd"/>

<plist version="1.0">
    <dict>
        <key>ROOT</key>
        <array>
            <dict>
                <key>id</key>
                <string>117</string>
                <key>className</key>
                <string>PTModelObjectButton</string>
                <key>Name</key>
                <dict>
                    <key>value</key>
                    <string>Pause</string>
                </dict>
                <key>Position</key>
                <dict>
                    <key>value</key>
                    <string>{545.775,1032.775}</string>
                </dict>
                <key>Scale</key>
                <dict>
                    <key>value</key>
                    <string>{0.151,0.151}</string>
                </dict>
                <key>Hidden</key>
                <dict>
                    <key>visible</key>
                    <string>0</string>
                </dict>
                <key>Locked</key>
                <dict>
                    <key>visible</key>
                    <string>0</string>
                </dict>
                <key>Stick To Edge</key>
                <dict>
                    <key>value</key>
                    <string>0</string>
                </dict>
                <key>Action</key>
                <dict>
                    <key>selectedStringValue</key>
                    <string>kPauseButton</string>
                </dict>
                <key>Back To</key>
                <dict>
                    <key>visible</key>
                    <string>0</string>
                    <key>selectedStringValue</key>
                    <string>PTPScreenMainMenuUI</string>
                </dict>
                <key>Back To World</key>
                <dict>
                    <key>visible</key>
                    <string>0</string>
                    <key>selectedStringValue</key>
                    <string></string>
                </dict>
                <key>Keyboard Key</key>
                <dict>
                    <key>value</key>
                    <string>-1</string>
                </dict>
                <key>Touch Emulation</key>
                <dict>
                    <key>visible</key>
                    <string>0</string>
                </dict>
                <key>zDepth</key>
                <string>6</string>
            </dict>
            <dict>
                <key>id</key>
                <string>126</string>
                <key>className</key>
                <string>PTModelObjectButton</string>
                <key>Name</key>
                <dict>
                    <key>value</key>
                    <string>Start</string>
                </dict>
                <key>Position</key>
                <dict>
                    <key>value</key>
                    <string>{320.775,565.000}</string>
                </dict>
                <key>Scale</key>
                <dict>
                    <key>value</key>
                    <string>{0.870,0.870}</string>
                </dict>
                <key>Hidden</key>
                <dict>
                    <key>visible</key>
                    <string>0</string>
                </dict>
                <key>Locked</key>
                <dict>
                    <key>visible</key>
                    <string>0</string>
                </dict>
                <key>Action</key>
                <dict>
                    <key>selectedStringValue</key>
                    <string>kNoAction</string>
                </dict>
                <key>Back To</key>
                <dict>
                    <key>visible</key>
                    <string>0</string>
                    <key>selectedStringValue</key>
                    <string></string>
                </dict>
                <key>Back To World</key>
                <dict>
                    <key>visible</key>
                    <string>0</string>
                    <key>selectedStringValue</key>
                    <string></string>
                </dict>
                <key>Keyboard Key</key>
                <dict>
                    <key>value</key>
                    <string>-1</string>
                </dict>
                <key>Touch Emulation</key>
                <dict>
                    <key>visible</key>
                    <string>0</string>
                </dict>
                <key>zDepth</key>
                <string>2</string>
            </dict>
            <dict>
                <key>id</key>
                <string>132</string>
                <key>className</key>
                <string>PTModelObjectButton</string>
                <key>Name</key>
                <dict>
                    <key>value</key>
                    <string>Back</string>
                </dict>
                <key>Position</key>
                <dict>
                    <key>value</key>
                    <string>{78.954,1030.866}</string>
                </dict>
                <key>Scale</key>
                <dict>
                    <key>value</key>
                    <string>{0.763,0.763}</string>
                </dict>
                <key>Hidden</key>
                <dict>
                    <key>visible</key>
                    <string>0</string>
                </dict>
                <key>Locked</key>
                <dict>
                    <key>visible</key>
                    <string>0</string>
                </dict>
                <key>Stick To Edge</key>
                <dict>
                    <key>value</key>
                    <string>0</string>
                </dict>
                <key>Action</key>
                <dict>
                    <key>selectedStringValue</key>
                    <string>kBackToButton</string>
                </dict>
                <key>Back To</key>
                <dict>
                    <key>selectedStringValue</key>
                    <string>PTPScreenMainMenuUI</string>
                </dict>
                <key>Back To World</key>
                <dict>
                    <key>visible</key>
                    <string>0</string>
                    <key>selectedStringValue</key>
                    <string></string>
                </dict>
                <key>Keyboard Key</key>
                <dict>
                    <key>value</key>
                    <string>-1</string>
                </dict>
                <key>Touch Emulation</key>
                <dict>
                    <key>visible</key>
                    <string>0</string>
                </dict>
                <key>zDepth</key>
                <string>1</string>
            </dict>
            <dict>
                <key>id</key>
                <string>137</string>
                <key>className</key>
                <string>PTModelObjectButton</string>
                <key>Name</key>
                <dict>
                    <key>value</key>
                    <string>Info Screen</string>
                </dict>
                <key>Position</key>
                <dict>
                    <key>value</key>
                    <string>{550.040,71.817}</string>
                </dict>
                <key>Scale</key>
                <dict>
                    <key>value</key>
                    <string>{0.534,0.534}</string>
                </dict>
                <key>Hidden</key>
                <dict>
                    <key>visible</key>
                    <string>0</string>
                </dict>
                <key>Locked</key>
                <dict>
                    <key>visible</key>
                    <string>0</string>
                </dict>
                <key>Stick To Edge</key>
                <dict>
                    <key>value</key>
                    <string>0</string>
                </dict>
                <key>Action</key>
                <dict>
                    <key>selectedStringValue</key>
                    <string>kNoAction</string>
                </dict>
                <key>Back To</key>
                <dict>
                    <key>visible</key>
                    <string>0</string>
                    <key>selectedStringValue</key>
                    <string></string>
                </dict>
                <key>Back To World</key>
                <dict>
                    <key>visible</key>
                    <string>0</string>
                    <key>selectedStringValue</key>
                    <string></string>
                </dict>
                <key>Keyboard Key</key>
                <dict>
                    <key>value</key>
                    <string>-1</string>
                </dict>
                <key>Touch Emulation</key>
                <dict>
                    <key>visible</key>
                    <string>0</string>
                </dict>
                <key>zDepth</key>
                <string>3</string>
            </dict>
            <dict>
                <key>id</key>
                <string>167</string>
                <key>className</key>
                <string>PTModelObjectButton</string>
                <key>Name</key>
                <dict>
                    <key>value</key>
                    <string>Main Menu</string>
                </dict>
                <key>Position</key>
                <dict>
                    <key>value</key>
                    <string>{558.828,1030.417}</string>
                </dict>
                <key>Scale</key>
                <dict>
                    <key>value</key>
                    <string>{0.165,0.165}</string>
                </dict>
                <key>Hidden</key>
                <dict>
                    <key>visible</key>
                    <string>0</string>
                </dict>
                <key>Locked</key>
                <dict>
                    <key>visible</key>
                    <string>0</string>
                </dict>
                <key>Stick To Edge</key>
                <dict>
                    <key>value</key>
                    <string>0</string>
                </dict>
                <key>Action</key>
                <dict>
                    <key>selectedStringValue</key>
                    <string>kBackToButton</string>
                </dict>
                <key>Back To</key>
                <dict>
                    <key>selectedStringValue</key>
                    <string>PTPScreenMainMenuUI</string>
                </dict>
                <key>Back To World</key>
                <dict>
                    <key>visible</key>
                    <string>0</string>
                    <key>selectedStringValue</key>
                    <string></string>
                </dict>
                <key>Keyboard Key</key>
                <dict>
                    <key>value</key>
                    <string>-1</string>
                </dict>
                <key>Touch Emulation</key>
                <dict>
                    <key>visible</key>
                    <string>0</string>
                </dict>
                <key>zDepth</key>
                <string>4</string>
            </dict>
            <dict>
                <key>id</key>
                <string>3455</string>
                <key>className</key>
                <string>PTModelObjectButton</string>
                <key>Name</key>
                <dict>
                    <key>value</key>
                    <string>Navigation Button</string>
                </dict>
                <key>Position</key>
                <dict>
                    <key>value</key>
                    <string>{309.835,625.697}</string>
                </dict>
                <key>Scale</key>
                <dict>
                    <key>value</key>
                    <string>{1.000,1.000}</string>
                </dict>
                <key>Hidden</key>
                <dict>
                    <key>visible</key>
                    <string>0</string>
                </dict>
                <key>Locked</key>
                <dict>
                    <key>visible</key>
                    <string>0</string>
                </dict>
                <key>Action</key>
                <dict>
                    <key>selectedStringValue</key>
                    <string>kNoAction</string>
                </dict>
                <key>Back To</key>
                <dict>
                    <key>visible</key>
                    <string>0</string>
                    <key>selectedStringValue</key>
                    <string>PTPScreenMainMenuUI</string>
                </dict>
                <key>Back To World</key>
                <dict>
                    <key>visible</key>
                    <string>0</string>
                    <key>selectedStringValue</key>
                    <string></string>
                </dict>
                <key>Keyboard Key</key>
                <dict>
                    <key>value</key>
                    <string>-1</string>
                </dict>
                <key>Touch Emulation</key>
                <dict>
                    <key>visible</key>
                    <string>0</string>
                </dict>
                <key>zDepth</key>
                <string>1000</string>
            </dict>
            <dict>
                <key>id</key>
                <string>5481</string>
                <key>className</key>
                <string>PTModelObjectButton</string>
                <key>Name</key>
                <dict>
                    <key>value</key>
                    <string>Navigation Button</string>
                </dict>
                <key>Position</key>
                <dict>
                    <key>value</key>
                    <string>{408.342,82.757}</string>
                </dict>
                <key>Scale</key>
                <dict>
                    <key>value</key>
                    <string>{1.000,1.000}</string>
                </dict>
                <key>Hidden</key>
                <dict>
                    <key>visible</key>
                    <string>0</string>
                </dict>
                <key>Locked</key>
                <dict>
                    <key>visible</key>
                    <string>0</string>
                </dict>
                <key>Action</key>
                <dict>
                    <key>selectedStringValue</key>
                    <string>kNoAction</string>
                </dict>
                <key>Back To</key>
                <dict>
                    <key>visible</key>
                    <string>0</string>
                    <key>selectedStringValue</key>
                    <string>PTPScreenMainMenuUI</string>
                </dict>
                <key>Back To World</key>
                <dict>
                    <key>visible</key>
                    <string>0</string>
                    <key>selectedStringValue</key>
                    <string></string>
                </dict>
                <key>Keyboard Key</key>
                <dict>
                    <key>value</key>
                    <string>-1</string>
                </dict>
                <key>Touch Emulation</key>
                <dict>
                    <key>visible</key>
                    <string>0</string>
                </dict>
                <key>zDepth</key>
                <string>1000</string>
            </dict>
            <dict>
                <key>id</key>
                <string>5483</string>
                <key>className</key>
                <string>PTModelObjectButton</string>
                <key>Name</key>
                <dict>
                    <key>value</key>
                    <string>Navigation Button</string>
                </dict>
                <key>Position</key>
                <dict>
                    <key>value</key>
                    <string>{320.229,75.580}</string>
                </dict>
                <key>Scale</key>
                <dict>
                    <key>value</key>
                    <string>{0.844,0.844}</string>
                </dict>
                <key>Hidden</key>
                <dict>
                    <key>visible</key>
                    <string>0</string>
                </dict>
                <key>Locked</key>
                <dict>
                    <key>visible</key>
                    <string>0</string>
                </dict>
                <key>Action</key>
                <dict>
                    <key>selectedStringValue</key>
                    <string>kRestartButton</string>
                </dict>
                <key>Back To</key>
                <dict>
                    <key>visible</key>
                    <string>0</string>
                    <key>selectedStringValue</key>
                    <string>PTPScreenMainMenuUI</string>
                </dict>
                <key>Back To World</key>
                <dict>
                    <key>visible</key>
                    <string>0</string>
                    <key>selectedStringValue</key>
                    <string></string>
                </dict>
                <key>Keyboard Key</key>
                <dict>
                    <key>value</key>
                    <string>-1</string>
                </dict>
                <key>Touch Emulation</key>
                <dict>
                    <key>visible</key>
                    <string>0</string>
                </dict>
                <key>zDepth</key>
                <string>6</string>
            </dict>
            <dict>
                <key>id</key>
                <string>5493</string>
                <key>className</key>
                <string>PTModelObjectButton</string>
                <key>Name</key>
                <dict>
                    <key>value</key>
                    <string>Main Menu</string>
                </dict>
                <key>Position</key>
                <dict>
                    <key>value</key>
                    <string>{558.828,1030.417}</string>
                </dict>
                <key>Scale</key>
                <dict>
                    <key>value</key>
                    <string>{0.165,0.165}</string>
                </dict>
                <key>Hidden</key>
                <dict>
                    <key>visible</key>
                    <string>0</string>
                </dict>
                <key>Locked</key>
                <dict>
                    <key>visible</key>
                    <string>0</string>
                </dict>
                <key>Stick To Edge</key>
                <dict>
                    <key>value</key>
                    <string>0</string>
                </dict>
                <key>Action</key>
                <dict>
                    <key>selectedStringValue</key>
                    <string>kBackToButton</string>
                </dict>
                <key>Back To</key>
                <dict>
                    <key>selectedStringValue</key>
                    <string>PTPScreenMainMenuUI</string>
                </dict>
                <key>Back To World</key>
                <dict>
                    <key>visible</key>
                    <string>0</string>
                    <key>selectedStringValue</key>
                    <string></string>
                </dict>
                <key>Keyboard Key</key>
                <dict>
                    <key>value</key>
                    <string>-1</string>
                </dict>
                <key>Touch Emulation</key>
                <dict>
                    <key>visible</key>
                    <string>0</string>
                </dict>
                <key>zDepth</key>
                <string>5</string>
            </dict>
            <dict>
                <key>id</key>
                <string>5498</string>
                <key>className</key>
                <string>PTModelObjectButton</string>
                <key>Name</key>
                <dict>
                    <key>value</key>
                    <string>Navigation Button</string>
                </dict>
                <key>Position</key>
                <dict>
                    <key>value</key>
                    <string>{320.229,75.580}</string>
                </dict>
                <key>Scale</key>
                <dict>
                    <key>value</key>
                    <string>{0.844,0.844}</string>
                </dict>
                <key>Hidden</key>
                <dict>
                    <key>visible</key>
                    <string>0</string>
                </dict>
                <key>Locked</key>
                <dict>
                    <key>visible</key>
                    <string>0</string>
                </dict>
                <key>Action</key>
                <dict>
                    <key>selectedStringValue</key>
                    <string>kBackButton</string>
                </dict>
                <key>Back To</key>
                <dict>
                    <key>visible</key>
                    <string>0</string>
                    <key>selectedStringValue</key>
                    <string>PTPScreenMainMenuUI</string>
                </dict>
                <key>Back To World</key>
                <dict>
                    <key>visible</key>
                    <string>0</string>
                    <key>selectedStringValue</key>
                    <string></string>
                </dict>
                <key>Keyboard Key</key>
                <dict>
                    <key>value</key>
                    <string>-1</string>
                </dict>
                <key>Touch Emulation</key>
                <dict>
                    <key>visible</key>
                    <string>0</string>
                </dict>
                <key>zDepth</key>
                <string>6</string>
            </dict>
            <dict>
                <key>id</key>
                <string>6221</string>
                <key>className</key>
                <string>PTModelObjectButton</string>
                <key>Name</key>
                <dict>
                    <key>value</key>
                    <string>Navigation Button 2</string>
                </dict>
                <key>Position</key>
                <dict>
                    <key>value</key>
                    <string>{-235.620,707.636}</string>
                </dict>
                <key>Scale</key>
                <dict>
                    <key>value</key>
                    <string>{1.000,1.000}</string>
                </dict>
                <key>Hidden</key>
                <dict>
                    <key>visible</key>
                    <string>0</string>
                </dict>
                <key>Locked</key>
                <dict>
                    <key>visible</key>
                    <string>0</string>
                </dict>
                <key>Action</key>
                <dict>
                    <key>selectedStringValue</key>
                    <string>kNoAction</string>
                </dict>
                <key>Back To</key>
                <dict>
                    <key>visible</key>
                    <string>0</string>
                    <key>selectedStringValue</key>
                    <string>PTPScreenMainMenuUI</string>
                </dict>
                <key>Back To World</key>
                <dict>
                    <key>visible</key>
                    <string>0</string>
                    <key>selectedStringValue</key>
                    <string></string>
                </dict>
                <key>Keyboard Key</key>
                <dict>
                    <key>value</key>
                    <string>-1</string>
                </dict>
                <key>Touch Emulation</key>
                <dict>
                    <key>visible</key>
                    <string>0</string>
                </dict>
                <key>zDepth</key>
                <string>1000</string>
            </dict>
            <dict>
                <key>id</key>
                <string>6226</string>
                <key>className</key>
                <string>PTModelObjectButton</string>
                <key>Name</key>
                <dict>
                    <key>value</key>
                    <string>Navigation Button 2</string>
                </dict>
                <key>Position</key>
                <dict>
                    <key>value</key>
                    <string>{368.157,408.460}</string>
                </dict>
                <key>Scale</key>
                <dict>
                    <key>value</key>
                    <string>{1.000,1.000}</string>
                </dict>
                <key>Hidden</key>
                <dict>
                    <key>visible</key>
                    <string>0</string>
                </dict>
                <key>Locked</key>
                <dict>
                    <key>visible</key>
                    <string>0</string>
                </dict>
                <key>Action</key>
                <dict>
                    <key>selectedStringValue</key>
                    <string>kNoAction</string>
                </dict>
                <key>Back To</key>
                <dict>
                    <key>visible</key>
                    <string>0</string>
                    <key>selectedStringValue</key>
                    <string>PTPScreenMainMenuUI</string>
                </dict>
                <key>Back To World</key>
                <dict>
                    <key>visible</key>
                    <string>0</string>
                    <key>selectedStringValue</key>
                    <string></string>
                </dict>
                <key>Keyboard Key</key>
                <dict>
                    <key>value</key>
                    <string>-1</string>
                </dict>
                <key>Touch Emulation</key>
                <dict>
                    <key>visible</key>
                    <string>0</string>
                </dict>
                <key>zDepth</key>
                <string>1000</string>
            </dict>
            <dict>
                <key>id</key>
                <string>6489</string>
                <key>className</key>
                <string>PTModelObjectButton</string>
                <key>Name</key>
                <dict>
                    <key>value</key>
                    <string>Main Menu</string>
                </dict>
                <key>Position</key>
                <dict>
                    <key>value</key>
                    <string>{558.828,1030.417}</string>
                </dict>
                <key>Scale</key>
                <dict>
                    <key>value</key>
                    <string>{0.165,0.165}</string>
                </dict>
                <key>Hidden</key>
                <dict>
                    <key>visible</key>
                    <string>0</string>
                </dict>
                <key>Locked</key>
                <dict>
                    <key>visible</key>
                    <string>0</string>
                </dict>
                <key>Stick To Edge</key>
                <dict>
                    <key>value</key>
                    <string>0</string>
                </dict>
                <key>Action</key>
                <dict>
                    <key>selectedStringValue</key>
                    <string>kBackToButton</string>
                </dict>
                <key>Back To</key>
                <dict>
                    <key>selectedStringValue</key>
                    <string></string>
                </dict>
                <key>Back To World</key>
                <dict>
                    <key>visible</key>
                    <string>0</string>
                    <key>selectedStringValue</key>
                    <string></string>
                </dict>
                <key>Keyboard Key</key>
                <dict>
                    <key>value</key>
                    <string>-1</string>
                </dict>
                <key>Touch Emulation</key>
                <dict>
                    <key>visible</key>
                    <string>0</string>
                </dict>
                <key>zDepth</key>
                <string>5</string>
            </dict>
            <dict>
                <key>id</key>
                <string>6494</string>
                <key>className</key>
                <string>PTModelObjectButton</string>
                <key>Name</key>
                <dict>
                    <key>value</key>
                    <string>Navigation Button</string>
                </dict>
                <key>Position</key>
                <dict>
                    <key>value</key>
                    <string>{320.229,75.580}</string>
                </dict>
                <key>Scale</key>
                <dict>
                    <key>value</key>
                    <string>{0.844,0.844}</string>
                </dict>
                <key>Hidden</key>
                <dict>
                    <key>visible</key>
                    <string>0</string>
                </dict>
                <key>Locked</key>
                <dict>
                    <key>visible</key>
                    <string>0</string>
                </dict>
                <key>Action</key>
                <dict>
                    <key>selectedStringValue</key>
                    <string>kBackButton</string>
                </dict>
                <key>Back To</key>
                <dict>
                    <key>visible</key>
                    <string>0</string>
                    <key>selectedStringValue</key>
                    <string></string>
                </dict>
                <key>Back To World</key>
                <dict>
                    <key>visible</key>
                    <string>0</string>
                    <key>selectedStringValue</key>
                    <string></string>
                </dict>
                <key>Keyboard Key</key>
                <dict>
                    <key>value</key>
                    <string>-1</string>
                </dict>
                <key>Touch Emulation</key>
                <dict>
                    <key>visible</key>
                    <string>0</string>
                </dict>
                <key>zDepth</key>
                <string>6</string>
            </dict>
            <dict>
                <key>id</key>
                <string>6812</string>
                <key>className</key>
                <string>PTModelObjectButton</string>
                <key>Name</key>
                <dict>
                    <key>value</key>
                    <string>Game Center</string>
                </dict>
                <key>Position</key>
                <dict>
                    <key>value</key>
                    <string>{93.668,71.817}</string>
                </dict>
                <key>Scale</key>
                <dict>
                    <key>value</key>
                    <string>{0.534,0.534}</string>
                </dict>
                <key>Hidden</key>
                <dict>
                    <key>visible</key>
                    <string>0</string>
                </dict>
                <key>Locked</key>
                <dict>
                    <key>visible</key>
                    <string>0</string>
                </dict>
                <key>Stick To Edge</key>
                <dict>
                    <key>value</key>
                    <string>0</string>
                </dict>
                <key>Action</key>
                <dict>
                    <key>selectedStringValue</key>
                    <string>kGameServices</string>
                </dict>
                <key>Back To</key>
                <dict>
                    <key>visible</key>
                    <string>0</string>
                    <key>selectedStringValue</key>
                    <string></string>
                </dict>
                <key>Back To World</key>
                <dict>
                    <key>visible</key>
                    <string>0</string>
                    <key>selectedStringValue</key>
                    <string></string>
                </dict>
                <key>Keyboard Key</key>
                <dict>
                    <key>value</key>
                    <string>-1</string>
                </dict>
                <key>Touch Emulation</key>
                <dict>
                    <key>visible</key>
                    <string>0</string>
                </dict>
                <key>zDepth</key>
                <string>4</string>
            </dict>
            <dict>
                <key>id</key>
                <string>6823</string>
                <key>className</key>
                <string>PTModelObjectButton</string>
                <key>Name</key>
                <dict>
                    <key>value</key>
                    <string>Share</string>
                </dict>
                <key>Position</key>
                <dict>
                    <key>value</key>
                    <string>{86.828,344.587}</string>
                </dict>
                <key>Scale</key>
                <dict>
                    <key>value</key>
                    <string>{0.534,0.534}</string>
                </dict>
                <key>Hidden</key>
                <dict>
                    <key>visible</key>
                    <string>0</string>
                </dict>
                <key>Locked</key>
                <dict>
                    <key>visible</key>
                    <string>0</string>
                </dict>
                <key>Stick To Edge</key>
                <dict>
                    <key>value</key>
                    <string>0</string>
                </dict>
                <key>Action</key>
                <dict>
                    <key>selectedStringValue</key>
                    <string>kShareButton</string>
                </dict>
                <key>Back To</key>
                <dict>
                    <key>visible</key>
                    <string>0</string>
                    <key>selectedStringValue</key>
                    <string>PTPScreenMainMenuUI</string>
                </dict>
                <key>Back To World</key>
                <dict>
                    <key>visible</key>
                    <string>0</string>
                    <key>selectedStringValue</key>
                    <string></string>
                </dict>
                <key>Keyboard Key</key>
                <dict>
                    <key>value</key>
                    <string>-1</string>
                </dict>
                <key>Touch Emulation</key>
                <dict>
                    <key>visible</key>
                    <string>0</string>
                </dict>
                <key>zDepth</key>
                <string>5</string>
            </dict>
        </array>
    </dict>
</plist>
